tei_rdfa/__init__.py
tei_rdfa/requirements.txt
tei_rdfa/ipynb/tei_rdfa.ipynb
tei_rdfa-0.1.0b4.dist-info/METADATA
tei_rdfa-0.1.0b4.dist-info/WHEEL
tei_rdfa-0.1.0b4.dist-info/licenses/LICENSE
tei_rdfa-0.1.0b4.dist-info/RECORD
