Metadata-Version: 2.4
Name: tei_rdfa
Version: 0.1.0b4
Summary: A Python utility for extracting RDFa data from TEI-XML documents.
Project-URL: Homepage, https://github.com/timofruehwirth/tei_rdfa
Project-URL: Issues, https://github.com/timofruehwirth/tei_rdfa/issues
Author-email: Timo Frühwirth <timo.fruehwirth@oeaw.ac.at>
License-Expression: GPL-3.0
License-File: LICENSE
Classifier: Operating System :: OS Independent
Classifier: Programming Language :: Python :: 3
Requires-Python: >=3.8
Requires-Dist: lxml>=5.1.1
Requires-Dist: rdflib>=6.2.0
